{"api_animation.md":"73d30656","guide_tutorial_measure.md":"86b91a80","guide_tutorial_coord.md":"cb468906","auth_index.md":"434cdefa","public_sandbox_pages_readme.md":"bec23cf1","guide_introduction.md":"98796bb7","guide_tutorial_iot.md":"ec1e26f5","api_tool.md":"ee8562d2","cli_index.md":"21d48ddb","guide_advanced_async.md":"17fdca18","community_wechat_index.md":"32e69a71","api_kapi.md":"085b62d5","guide_translate.md":"ed1492d0","guide_tutorial_scene.md":"b54bcad0","api_measure.md":"11c5e302","examples_index.md":"c4f9446e","guide_tutorial_data.md":"725212b6","guide_tools_cli.md":"7a66f852","guide_tutorial_ui.md":"733f9a33","guide_tutorial_analyze.md":"035a0d1a","case_index.md":"ec75da6f","tool_index.md":"ea9edf95","guide_tutorial_layer.md":"af3d50a8","guide_tutorial_tool.md":"55167745","sponsor_index.md":"7988d40a","guide_advanced_plugins.md":"1313481b","guide_tools_tool.md":"d50d8c97","api_camera.md":"5703cc21","api_application.md":"3f94f6c5","guide_versions.md":"227ff94e","guide_tutorial_event.md":"96bf058e","public_sandbox_pages_demo_b.md":"23179873","guide_environment.md":"8027aea4","api_layer.md":"afa4cdb3","guide_auth.md":"6c2a62cc","api_iot.md":"e4af2ddb","api_scene.md":"9540de90","learn_docker_introduction.md":"231be912","guide_installation.md":"c82d32a3","guide_tutorial_draw.md":"fed52e13","guide_help.md":"4ccd29f3","guide_tutorial_camera.md":"eb34f451","api_controller.md":"b7e2224e","api_kapi-const.md":"58267e98","guide_quick-start.md":"79caac42","community_qq_index.md":"bb5632b0","guide_tutorial_marker.md":"ee875494","api_data.md":"fe38de58","api_event.md":"2c373d67","guide_tutorial_controller.md":"d445b2a1","public_sandbox_pages_start_introduction.md":"9ada87bb","learn_linux_introduction.md":"c1118f45","index.md":"de99ca78","api_index.md":"36ad2f95","api_analyze.md":"9e58d66c","api_draw.md":"365ec6ca","api_marker.md":"6ea40612","translations_index.md":"06b54ba9","guide_instance.md":"26500470","learn_devops_introduction.md":"91f94eb0","api_coord.md":"78be3adc","api_ui.md":"7d1101a4"}
